astraforge_toolkit/__init__.py
astraforge_toolkit/backend.py
astraforge_toolkit/client.py
astraforge_toolkit/tools.py
astraforge_toolkit-0.1.10.dist-info/licenses/LICENSE
astraforge_toolkit-0.1.10.dist-info/METADATA
astraforge_toolkit-0.1.10.dist-info/WHEEL
astraforge_toolkit-0.1.10.dist-info/top_level.txt
astraforge_toolkit-0.1.10.dist-info/RECORD
