Metadata-Version: 2.4
Name: astraforge-toolkit
Version: 0.1.10
Summary: HTTP client and sandbox backend for AstraForge DeepAgent.
Author-email: AstraForge Contributors <jeremy.jouvance@gmail.com>
License: MIT License
Classifier: License :: OSI Approved :: MIT License
Classifier: Programming Language :: Python :: 3 :: Only
Classifier: Programming Language :: Python :: 3.11
Requires-Python: >=3.11
License-File: LICENSE
Requires-Dist: requests>=2.32
Requires-Dist: deepagents>=0.2.8
Provides-Extra: dev
Requires-Dist: pytest; extra == "dev"
Requires-Dist: types-requests; extra == "dev"
Dynamic: license-file
